MANIFEST.in
setup.py
anthill/leaderboard/__init__.py
anthill/leaderboard/admin.py
anthill/leaderboard/handler.py
anthill/leaderboard/options.py
anthill/leaderboard/server.py
anthill/leaderboard/model/__init__.py
anthill/leaderboard/model/leaderboard.py
anthill/leaderboard/model/social.py
anthill/leaderboard/sql/leaderboard_cluster_accounts.sql
anthill/leaderboard/sql/leaderboard_clusters.sql
anthill/leaderboard/sql/leaderboards.sql
anthill/leaderboard/sql/records.sql
anthill/leaderboard/sql/records_expiration.sql
anthill_leaderboard.egg-info/PKG-INFO
anthill_leaderboard.egg-info/SOURCES.txt
anthill_leaderboard.egg-info/dependency_links.txt
anthill_leaderboard.egg-info/namespace_packages.txt
anthill_leaderboard.egg-info/not-zip-safe
anthill_leaderboard.egg-info/requires.txt
anthill_leaderboard.egg-info/top_level.txt