Metadata-Version: 1.0
Name: anthill-leaderboard
Version: 0.2
Summary: User ranking service for Anthill Platform
Home-page: https://github.com/anthill-platform/anthill-leaderboard
Author: desertkun
Author-email: desertkun@gmail.com
License: MIT
Platform: UNKNOWN
